kurt/__init__.py
kurt/plugin.py
kurt/text.py
kurt/scratch14/__init__.py
kurt/scratch14/blocks.py
kurt/scratch14/blockspecs_src.py
kurt/scratch14/fixed_objects.py
kurt/scratch14/heights.py
kurt/scratch14/inline_objects.py
kurt/scratch14/objtable.py
kurt/scratch14/user_objects.py
kurt/scratch20/__init__.py
kurt/scratch20/blocks.py
kurt/scratch20/commands_src.py
kurt-2.0.6.data/scripts/kurtc.py
kurt-2.0.6.data/scripts/kurtgui.py
kurt-2.0.6.dist-info/DESCRIPTION.rst
kurt-2.0.6.dist-info/METADATA
kurt-2.0.6.dist-info/metadata.json
kurt-2.0.6.dist-info/RECORD
kurt-2.0.6.dist-info/top_level.txt
kurt-2.0.6.dist-info/WHEEL
