Metadata-Version: 2.0
Name: kurt
Version: 2.0.6
Summary: Library for reading/writing MIT's Scratch file format.
Home-page: https://github.com/blob8108/kurt
Author: Tim Radvan
Author-email: blob8108@gmail.com
License: LGPL
Keywords: scratch
Platform: UNKNOWN
Classifier: Programming Language :: Python
Classifier: License :: OSI Approved :: GNU Lesser General Public License v3 or later (LGPLv3+)
Classifier: Operating System :: OS Independent
Classifier: Development Status :: 4 - Beta
Classifier: Intended Audience :: Developers
Classifier: Intended Audience :: End Users/Desktop
Classifier: Intended Audience :: Education
Classifier: Environment :: Console
Classifier: Topic :: Software Development :: Libraries :: Python Modules
Classifier: Topic :: Education
Requires-Dist: construct (==2.0.6)
Requires-Dist: pillow (>=2.0)
